{
  "project_info": {
    "project_number": "685021951846",
    "firebase_url": "https://frndszone-3aab7.firebaseio.com",
    "project_id": "frndszone-3aab7",
    "storage_bucket": "frndszone-3aab7.appspot.com"
  },
  "client": [
    {
      "client_info": {
        "mobilesdk_app_id": "1:685021951846:android:88ec0d43832ad0da6a7aa7",
        "android_client_info": {
          "package_name": "com.example.frndszone"
        }
      },
      "oauth_client": [
        {
          "client_id": "685021951846-7ovl9alnami6v9qhmp46bu0ao3gdnc6l.apps.googleusercontent.com",
          "client_type": 1,
          "android_info": {
            "package_name": "com.example.frndszone",
            "certificate_hash": "3ecb2d6dd39128a0295a420a9f58bf7a066b106e"
          }
        },
        {
          "client_id": "685021951846-3pdj4btbq6ht3c7kvrroj6stjkadsrdb.apps.googleusercontent.com",
          "client_type": 3
        }
      ],
      "api_key": [
        {
          "current_key": "AIzaSyDYRvFyOfSbFIUnb7LQOEDgQMdhizgnTkQ"
        }
      ],
      "services": {
        "appinvite_service": {
          "other_platform_oauth_client": [
            {
              "client_id": "685021951846-3pdj4btbq6ht3c7kvrroj6stjkadsrdb.apps.googleusercontent.com",
              "client_type": 3
            }
          ]
        }
      }
    }
  ],
  "configuration_version": "1"
}